[
    {
        "Topic":-1,
        "Count":1783,
        "Name":"-1_workflow_dataset_batch_transform job"
    },
    {
        "Topic":0,
        "Count":257,
        "Name":"0_git repo_git command_git repositori_git"
    },
    {
        "Topic":1,
        "Count":241,
        "Name":"1_chart_line chart_chart run_chart chart"
    },
    {
        "Topic":2,
        "Count":164,
        "Name":"2_instal modulenotfounderror_instal pip_pip instal_instal packag"
    },
    {
        "Topic":3,
        "Count":153,
        "Name":"3_model docker_docker model_dockerfil_built docker"
    },
    {
        "Topic":4,
        "Count":128,
        "Name":"4_invoc endpoint_invok endpoint_endpoint api_endpoint involv"
    },
    {
        "Topic":5,
        "Count":115,
        "Name":"5_pipelin execut_run pipelin_pipelin run_pipelin devop"
    },
    {
        "Topic":6,
        "Count":101,
        "Name":"6_autom forecast_forecast autom_model forecast_predict data"
    },
    {
        "Topic":7,
        "Count":96,
        "Name":"7_jupyterlab notebook_jupyt notebook_notebook jupyt_notebook environ"
    },
    {
        "Topic":8,
        "Count":78,
        "Name":"8_commun support_feedback forward_acknowledg feedback_feedback implement"
    },
    {
        "Topic":9,
        "Count":72,
        "Name":"9_artifact log_artifact command_log artifact_artifact api"
    },
    {
        "Topic":10,
        "Count":72,
        "Name":"10_gpu model_gpu specif_gpu train_gpu memori"
    },
    {
        "Topic":11,
        "Count":63,
        "Name":"11_sweep config_sweep configur_sweep command_run sweep"
    },
    {
        "Topic":12,
        "Count":60,
        "Name":"12_model xgboost_train xgboost_xgboost model_run xgboost"
    },
    {
        "Topic":13,
        "Count":59,
        "Name":"13_panda datafram_datafram panda_panda csv_csv panda"
    },
    {
        "Topic":14,
        "Count":57,
        "Name":"14_column_sql transform_column valu_column dataset"
    },
    {
        "Topic":15,
        "Count":55,
        "Name":"15_autom data_label job_label train_autom label"
    },
    {
        "Topic":16,
        "Count":46,
        "Name":"16_download dataset_dataset download_creat dataset_import data"
    },
    {
        "Topic":17,
        "Count":41,
        "Name":"17_endpoint model_model endpoint_endpoint multi_model multi"
    },
    {
        "Topic":18,
        "Count":41,
        "Name":"18_role access_account role_role permiss_execut role"
    },
    {
        "Topic":19,
        "Count":40,
        "Name":"19_support plan_support ticket_ticket support_support request"
    },
    {
        "Topic":20,
        "Count":40,
        "Name":"20_messag support_follow messag_messag seri_seri messag"
    },
    {
        "Topic":21,
        "Count":38,
        "Name":"21_speech api_cloud speech_speech text_text speech"
    },
    {
        "Topic":22,
        "Count":38,
        "Name":"22_comput instanc_perform cost_hour comput_avail instanc"
    },
    {
        "Topic":23,
        "Count":36,
        "Name":"23_vision api_document comprehend_ocr model_document text"
    },
    {
        "Topic":24,
        "Count":35,
        "Name":"24_spark environ_spark session_spark configur_sparkmag pyspark"
    },
    {
        "Topic":25,
        "Count":35,
        "Name":"25_model automl_automl model_export model_automl tabular"
    },
    {
        "Topic":26,
        "Count":35,
        "Name":"26_metric cloudwatch_cloudwatch creat_instanc cloudwatch_cloudwatch metric"
    },
    {
        "Topic":27,
        "Count":33,
        "Name":"27_request quota_comput quota_quota limit_limit quota"
    },
    {
        "Topic":28,
        "Count":33,
        "Name":"28_outfiledatasetconfig pipelinedata_outputdatasetconfig pipelinedata_output pipelinedata_outputfiledatasetconfig multiprocess"
    },
    {
        "Topic":29,
        "Count":32,
        "Name":"29_model path_model dir_model version_model regist"
    },
    {
        "Topic":30,
        "Count":31,
        "Name":"30_export data_databas export_sql databas_databas"
    },
    {
        "Topic":31,
        "Count":30,
        "Name":"31_run directori_directori run_directori path_folder directori"
    },
    {
        "Topic":32,
        "Count":28,
        "Name":"32_log debug_debug log_crash distribut_command debug"
    },
    {
        "Topic":33,
        "Count":27,
        "Name":"33_account resourc_account storag_account manag_account identifi"
    },
    {
        "Topic":34,
        "Count":27,
        "Name":"34_csv format_format csv_convert csv_text csv"
    },
    {
        "Topic":35,
        "Count":26,
        "Name":"35_train model_increment train_train channel_download train"
    },
    {
        "Topic":36,
        "Count":26,
        "Name":"36_configur vpc_connect vpc_vpc endpoint_vpc subnet"
    },
    {
        "Topic":37,
        "Count":26,
        "Name":"37_run tensorboard_tensorboard run_tensorboard command_command tensorboard"
    },
    {
        "Topic":38,
        "Count":25,
        "Name":"38_scriptrunconfig import_scriptrunconfig creat_scriptrunconfig_runconfigur scriptrunconfig"
    },
    {
        "Topic":39,
        "Count":24,
        "Name":"39_team email_com portal_email com_portal servic"
    },
    {
        "Topic":40,
        "Count":24,
        "Name":"40_upload dataset_upload data_data bucket_bucket upload"
    },
    {
        "Topic":41,
        "Count":24,
        "Name":"41_net model_cognit toolkit_neural network_learn implement"
    },
    {
        "Topic":42,
        "Count":23,
        "Name":"42_cluster comput_comput cluster_cluster configur_cluster creat"
    },
    {
        "Topic":43,
        "Count":23,
        "Name":"43_forest algorithm_random forest_forest model_tree model"
    },
    {
        "Topic":44,
        "Count":22,
        "Name":"44_api translat_translat api_document translat_translat code"
    },
    {
        "Topic":45,
        "Count":21,
        "Name":"45_learn studio_classic studio_resourc decemb_resourc recommend"
    },
    {
        "Topic":46,
        "Count":21,
        "Name":"46_delet data_delet command_run delet_delet script"
    },
    {
        "Topic":47,
        "Count":21,
        "Name":"47_notebook permiss_role notebook_permiss listnotebookinst_notebook account"
    },
    {
        "Topic":48,
        "Count":20,
        "Name":"48_process slow_job slow_slow perform_slow upload"
    },
    {
        "Topic":49,
        "Count":19,
        "Name":"49_notebook instanc_enabl notebook_referenc notebook_notebook access"
    },
    {
        "Topic":50,
        "Count":18,
        "Name":"50_hyperparamet tuner_hyperparamet tune_dataset hyperparamet_involv hyperparamet"
    },
    {
        "Topic":51,
        "Count":18,
        "Name":"51_kubernet cluster_kubernet servic_kubernet_deploi kubernet"
    },
    {
        "Topic":52,
        "Count":18,
        "Name":"52_checkpoint manual_manual checkpoint_execut checkpoint_implement checkpoint"
    },
    {
        "Topic":53,
        "Count":17,
        "Name":"53_retrain model_model retrain_retrain pipelin_train data"
    },
    {
        "Topic":54,
        "Count":17,
        "Name":"54_support respons_respons support_request support_respons request"
    },
    {
        "Topic":55,
        "Count":17,
        "Name":"55_process memori_memori command_memori profil_info memori"
    },
    {
        "Topic":56,
        "Count":16,
        "Name":"56_close repli_state close_close state_allow state"
    },
    {
        "Topic":57,
        "Count":16,
        "Name":"57_tabl view_column tabl_tab_tabl default"
    },
    {
        "Topic":58,
        "Count":16,
        "Name":"58_deploy troubleshoot_troubleshoot deploy_servic deploy_check deploy"
    },
    {
        "Topic":59,
        "Count":16,
        "Name":"59_bayesian optim_hyperparamet search_optimis_optim paramet"
    },
    {
        "Topic":60,
        "Count":16,
        "Name":"60_cluster parallel_parallel code_code parallel_comput cluster"
    },
    {
        "Topic":61,
        "Count":15,
        "Name":"61_bug avail_bug specif_report bug_bug activ"
    }
]